MuyunxiSupports/__init__.py
MuyunxiSupports/log.py
MuyunxiSupports/more_sys.py
MuyunxiSupports-0.1.1.dist-info/METADATA
MuyunxiSupports-0.1.1.dist-info/WHEEL
MuyunxiSupports-0.1.1.dist-info/top_level.txt
MuyunxiSupports-0.1.1.dist-info/RECORD
