Metadata-Version: 2.1
Name: MuyunxiSupports
Version: 0.1.1
Summary: Muyunxi's some Supports
Home-page: 
Author: Iewnfod
Author-email: 227919512@qq.com
Maintainer: Iewnfod
Maintainer-email: 227919512@qq.com
License: MIT License
Requires-Python: >=3.7
